litestar_email/__init__.py
litestar_email/config.py
litestar_email/exceptions.py
litestar_email/message.py
litestar_email/plugin.py
litestar_email/py.typed
litestar_email/service.py
litestar_email/backends/__init__.py
litestar_email/backends/base.py
litestar_email/backends/console.py
litestar_email/backends/mailgun.py
litestar_email/backends/memory.py
litestar_email/backends/resend.py
litestar_email/backends/sendgrid.py
litestar_email/backends/smtp.py
litestar_email/transports/__init__.py
litestar_email/transports/aiohttp.py
litestar_email/transports/base.py
litestar_email/transports/httpx.py
litestar_email/utils/__init__.py
litestar_email/utils/dependencies.py
litestar_email/utils/module_loader.py
litestar_email-0.3.0.dist-info/METADATA
litestar_email-0.3.0.dist-info/WHEEL
litestar_email-0.3.0.dist-info/licenses/LICENSE
litestar_email-0.3.0.dist-info/RECORD
