Metadata-Version: 2.4
Name: litestar-email
Version: 0.3.0
Summary: Email plugin for Litestar
Project-URL: Changelog, https://github.com/litestar-org/litestar-email/releases/
Project-URL: Discord, https://discord.gg/litestar-919193495116337154
Project-URL: Documentation, https://github.com/litestar-org/litestar-email
Project-URL: Homepage, https://github.com/litestar-org/litestar-email
Project-URL: Issue, https://github.com/litestar-org/litestar-email/issues/
Project-URL: Source, https://github.com/litestar-org/litestar-email
Author-email: Cody Fincher <cody@litestar.dev>
License: MIT
License-File: LICENSE
Keywords: email,litestar,mailgun,resend,sendgrid,smtp
Classifier: Development Status :: 3 - Alpha
Classifier: Environment :: Web Environment
Classifier: Intended Audience :: Developers
Classifier: License :: OSI Approved :: MIT License
Classifier: Natural Language :: English
Classifier: Operating System :: OS Independent
Classifier: Programming Language :: Python
Classifier: Programming Language :: Python :: 3.10
Classifier: Programming Language :: Python :: 3.11
Classifier: Programming Language :: Python :: 3.12
Classifier: Programming Language :: Python :: 3.13
Classifier: Topic :: Software Development
Classifier: Typing :: Typed
Requires-Python: >=3.10
Requires-Dist: litestar>=2.0.0
Requires-Dist: typing-extensions>=4.0.0
Provides-Extra: aiohttp
Requires-Dist: aiohttp>=3.9.0; extra == 'aiohttp'
Provides-Extra: all
Requires-Dist: aiohttp>=3.9.0; extra == 'all'
Requires-Dist: aiosmtplib>=3.0.0; extra == 'all'
Requires-Dist: httpx>=0.27.0; extra == 'all'
Provides-Extra: httpx
Requires-Dist: httpx>=0.27.0; extra == 'httpx'
Provides-Extra: smtp
Requires-Dist: aiosmtplib>=3.0.0; extra == 'smtp'
